xmlightning/__init__.py
xmlightning/core.py
xmlightning-0.1.8.dist-info/LICENSE
xmlightning-0.1.8.dist-info/METADATA
xmlightning-0.1.8.dist-info/WHEEL
xmlightning-0.1.8.dist-info/top_level.txt
xmlightning-0.1.8.dist-info/RECORD
