Metadata-Version: 2.1
Name: xmlightning
Version: 0.1.8
Summary: Allows you to create a simple and advanced xml parser
Home-page: https://github.com/beanowonotanuwu/xmlightning
Author: hunterg3
Author-email: hunterg123987@gmail.com
License: UNKNOWN
Platform: UNKNOWN
Classifier: Programming Language :: Python :: 3
Classifier: License :: OSI Approved :: MIT License
Classifier: Operating System :: OS Independent
Requires-Python: >=3.7
